pandora_online/PandoraOnline.py
pandora_online/__init__.py
pandora_online-0.4.dist-info/DESCRIPTION.rst
pandora_online-0.4.dist-info/METADATA
pandora_online-0.4.dist-info/RECORD
pandora_online-0.4.dist-info/WHEEL
pandora_online-0.4.dist-info/metadata.json
pandora_online-0.4.dist-info/top_level.txt
