Metadata-Version: 2.0
Name: pandora-online
Version: 0.4
Summary: The Pandora Online Class Helper
Home-page: http://github.com/vladimir1marchenko/pandora_oline
Author: Vladimir Marchenko
Author-email: vladimir1marchenko@gmail.com
License: MIT
Keywords: pandora pandect
Platform: UNKNOWN
